{
  "Python 注释_描述": {
    "prefix": ["xxx"],
    "body": [
      "#!/usr/bin/python",
      "# -*- coding: utf-8 -*-",
      "# Copyright (c) $CURRENT_YEAR, ${1:Administrator}. All rights reserved.",
      "# @Author  : ${1:Administrator}",
      "# @Date    : $CURRENT_YEAR-$CURRENT_MONTH-$CURRENT_DATE",
      "# @File    : $TM_FILENAME",
      "# @version : 0.0.1",
      "# @Desc    : ${2:描述}",
      "$0"
    ],
    "description": ["Python 注释_描述"]
  },
  "Python 常用导入": {
    "prefix": ["import==", "im=="],
    "body": [
      "import os",
      "import subprocess  # *执行系统命令模块",
      "import sys",
      "import zipfile",
      "from pathlib import Path",
      "",
      "$0"
    ],
    "description": ["Python 常用导入"]
  }
}
